MANIFEST.in
README-PyPI
README.rst
asc2eph.py
setup.py
Cdist/eph_manager.c
Cdist/eph_manager.h
Cdist/novas.c
Cdist/novas.h
Cdist/novascon.c
Cdist/novascon.h
Cdist/nutation.c
Cdist/nutation.h
Cdist/readeph0.c
Cdist/solarsystem.h
Cdist/solsys1.c
compat/__init__.py
compat/compat.py
compat/eph_manager.py
compat/nutation.py
compat/readeph0.py
compat/solsys.py
novas.egg-info/PKG-INFO
novas.egg-info/SOURCES.txt
novas.egg-info/dependency_links.txt
novas.egg-info/top_level.txt
novas_py/__init__.py
novas_py/constants.py
tests/__init__.py
tests/checkout-stars-full.py
tests/test_compat.py
tests/test_example.py
tests/test_github_issues.py