Metadata-Version: 2.1
Name: novas
Version: 3.1.1.6
Summary: The United States Naval Observatory NOVAS astronomy library
Home-page: http://www.usno.navy.mil/USNO/astronomical-applications/software-products/novas
Author: Eric G. Barron
Author-email: eric.barron@usno.navy.mil
Maintainer: Eric G. Barron; packaged for PyPI by Brandon Rhodes
Maintainer-email: brandon@rhodesmill.org
Platform: macosx
Platform: linux
Classifier: Development Status :: 5 - Production/Stable
Classifier: Intended Audience :: Science/Research
Classifier: Natural Language :: English
Classifier: Operating System :: MacOS :: MacOS X
Classifier: Operating System :: POSIX :: Linux
Classifier: Programming Language :: Python :: 2.7
Classifier: Programming Language :: Python :: 3.3
Classifier: Programming Language :: Python :: 3.4
Classifier: Programming Language :: Python :: 3.5
Classifier: Programming Language :: Python :: 3.6
Classifier: Programming Language :: Python :: 3.7
Classifier: Programming Language :: Python :: 3.8
Classifier: Programming Language :: Python :: 3.9
Classifier: Programming Language :: Python :: 3.10
Classifier: Programming Language :: Python :: 3.11
Classifier: Programming Language :: Python :: 3.12
Classifier: Topic :: Scientific/Engineering :: Astronomy
